MANIFEST.in
README.md
setup.py
doc/spec.md
src/anjuke/__init__.py
src/anjuke/pinyin/__init__.py
src/anjuke/pinyin/chars.txt
src/pinyin4py.egg-info/PKG-INFO
src/pinyin4py.egg-info/SOURCES.txt
src/pinyin4py.egg-info/dependency_links.txt
src/pinyin4py.egg-info/not-zip-safe
src/pinyin4py.egg-info/top_level.txt
test/tests.py